[
  {
    "month": "2024-03",
    "ms": 217748583,
    "plays": 1129,
    "hours": 60.49
  },
  {
    "month": "2024-04",
    "ms": 313946644,
    "plays": 1646,
    "hours": 87.21
  },
  {
    "month": "2024-05",
    "ms": 415535007,
    "plays": 2239,
    "hours": 115.43
  },
  {
    "month": "2024-06",
    "ms": 364555882,
    "plays": 1986,
    "hours": 101.27
  },
  {
    "month": "2024-07",
    "ms": 158344798,
    "plays": 1017,
    "hours": 43.98
  },
  {
    "month": "2024-08",
    "ms": 268277724,
    "plays": 1458,
    "hours": 74.52
  },
  {
    "month": "2024-09",
    "ms": 226471251,
    "plays": 1286,
    "hours": 62.91
  },
  {
    "month": "2024-10",
    "ms": 210320906,
    "plays": 1133,
    "hours": 58.42
  },
  {
    "month": "2024-11",
    "ms": 319759960,
    "plays": 1706,
    "hours": 88.82
  },
  {
    "month": "2024-12",
    "ms": 206038549,
    "plays": 1232,
    "hours": 57.23
  },
  {
    "month": "2025-01",
    "ms": 293664569,
    "plays": 1678,
    "hours": 81.57
  },
  {
    "month": "2025-02",
    "ms": 269292582,
    "plays": 1470,
    "hours": 74.8
  },
  {
    "month": "2025-03",
    "ms": 168879278,
    "plays": 837,
    "hours": 46.91
  }
]
